manim_presentation/__init__.py
manim_presentation/present.py
manim_presentation/slide.py
manim_presentation/wizard.py
manim_presentation-0.2.1.dist-info/LICENSE
manim_presentation-0.2.1.dist-info/METADATA
manim_presentation-0.2.1.dist-info/WHEEL
manim_presentation-0.2.1.dist-info/entry_points.txt
manim_presentation-0.2.1.dist-info/top_level.txt
manim_presentation-0.2.1.dist-info/RECORD
