Metadata-Version: 2.1
Name: manim-presentation
Version: 0.2.1
Summary: Tool for live presentations using manim
Home-page: https://github.com/galatolofederico/manim-presentation
Author: Federico A. Galatolo
Author-email: federico.galatolo@ing.unipi.it
License: UNKNOWN
Platform: UNKNOWN
Classifier: Programming Language :: Python :: 3.7
Classifier: License :: OSI Approved :: GNU General Public License v3 (GPLv3)
Classifier: Operating System :: OS Independent
Classifier: Development Status :: 4 - Beta
License-File: LICENSE
